HISTORY.rst
LICENSE
MANIFEST.in
README.rst
setup.cfg
setup.py
pyramid_tinymce_spellchecker/__init__.py
pyramid_tinymce_spellchecker/views.py
pyramid_tinymce_spellchecker.egg-info/PKG-INFO
pyramid_tinymce_spellchecker.egg-info/SOURCES.txt
pyramid_tinymce_spellchecker.egg-info/dependency_links.txt
pyramid_tinymce_spellchecker.egg-info/entry_points.txt
pyramid_tinymce_spellchecker.egg-info/not-zip-safe
pyramid_tinymce_spellchecker.egg-info/requires.txt
pyramid_tinymce_spellchecker.egg-info/top_level.txt
pyramid_tinymce_spellchecker/tests/__init__.py
pyramid_tinymce_spellchecker/tests/test_views.py