Metadata-Version: 1.1
Name: pyramid-tinymce-spellchecker
Version: 0.1
Summary: Pyramid glue for different tinymce spellchecker backends
Home-page: https://github.com/iElectric/pyramid_tinymce_spellchecker
Author: Domen Kožar
Author-email: domen@dev.si
License: BSD
Platform: UNKNOWN
Classifier: Programming Language :: Python
